{
  "__data_type": "UTC ",
  "Appearance_Type": {
    "type": "word",
    "value": 193
  },
  "BodyBag": {
    "type": "byte",
    "value": 0
  },
  "Cha": {
    "type": "byte",
    "value": 10
  },
  "ChallengeRating": {
    "type": "float",
    "value": 27.0
  },
  "ClassList": {
    "type": "list",
    "value": [
      {
        "__struct_id": 2,
        "Class": {
          "type": "int",
          "value": 5
        },
        "ClassLevel": {
          "type": "short",
          "value": 30
        }
      },
      {
        "__struct_id": 2,
        "Class": {
          "type": "int",
          "value": 7
        },
        "ClassLevel": {
          "type": "short",
          "value": 30
        },
        "MemorizedList1": {
          "type": "list",
          "value": [
            {
              "__struct_id": 3,
              "Spell": {
                "type": "word",
                "value": 421
              },
              "SpellFlags": {
                "type": "byte",
                "value": 1
              },
              "SpellMetaMagic": {
                "type": "byte",
                "value": 0
              }
            },
            {
              "__struct_id": 3,
              "Spell": {
                "type": "word",
                "value": 32
              },
              "SpellFlags": {
                "type": "byte",
                "value": 1
              },
              "SpellMetaMagic": {
                "type": "byte",
                "value": 0
              }
            },
            {
              "__struct_id": 3,
              "Spell": {
                "type": "word",
                "value": 53
              },
              "SpellFlags": {
                "type": "byte",
                "value": 1
              },
              "SpellMetaMagic": {
                "type": "byte",
                "value": 0
              }
            },
            {
              "__struct_id": 3,
              "Spell": {
                "type": "word",
                "value": 66
              },
              "SpellFlags": {
                "type": "byte",
                "value": 1
              },
              "SpellMetaMagic": {
                "type": "byte",
                "value": 0
              }
            },
            {
              "__struct_id": 3,
              "Spell": {
                "type": "word",
                "value": 452
              },
              "SpellFlags": {
                "type": "byte",
                "value": 1
              },
              "SpellMetaMagic": {
                "type": "byte",
                "value": 0
              }
            }
          ]
        },
        "MemorizedList2": {
          "type": "list",
          "value": [
            {
              "__struct_id": 3,
              "Spell": {
                "type": "word",
                "value": 13
              },
              "SpellFlags": {
                "type": "byte",
                "value": 1
              },
              "SpellMetaMagic": {
                "type": "byte",
                "value": 0
              }
            },
            {
              "__struct_id": 3,
              "Spell": {
                "type": "word",
                "value": 420
              },
              "SpellFlags": {
                "type": "byte",
                "value": 1
              },
              "SpellMetaMagic": {
                "type": "byte",
                "value": 0
              }
            },
            {
              "__struct_id": 3,
              "Spell": {
                "type": "word",
                "value": 137
              },
              "SpellFlags": {
                "type": "byte",
                "value": 1
              },
              "SpellMetaMagic": {
                "type": "byte",
                "value": 0
              }
            },
            {
              "__struct_id": 3,
              "Spell": {
                "type": "word",
                "value": 165
              },
              "SpellFlags": {
                "type": "byte",
                "value": 1
              },
              "SpellMetaMagic": {
                "type": "byte",
                "value": 0
              }
            }
          ]
        },
        "MemorizedList3": {
          "type": "list",
          "value": [
            {
              "__struct_id": 3,
              "Spell": {
                "type": "word",
                "value": 34
              },
              "SpellFlags": {
                "type": "byte",
                "value": 1
              },
              "SpellMetaMagic": {
                "type": "byte",
                "value": 0
              }
            },
            {
              "__struct_id": 3,
              "Spell": {
                "type": "word",
                "value": 453
              },
              "SpellFlags": {
                "type": "byte",
                "value": 1
              },
              "SpellMetaMagic": {
                "type": "byte",
                "value": 0
              }
            },
            {
              "__struct_id": 3,
              "Spell": {
                "type": "word",
                "value": 91
              },
              "SpellFlags": {
                "type": "byte",
                "value": 1
              },
              "SpellMetaMagic": {
                "type": "byte",
                "value": 0
              }
            },
            {
              "__struct_id": 3,
              "Spell": {
                "type": "word",
                "value": 176
              },
              "SpellFlags": {
                "type": "byte",
                "value": 1
              },
              "SpellMetaMagic": {
                "type": "byte",
                "value": 0
              }
            }
          ]
        },
        "MemorizedList4": {
          "type": "list",
          "value": [
            {
              "__struct_id": 3,
              "Spell": {
                "type": "word",
                "value": 35
              },
              "SpellFlags": {
                "type": "byte",
                "value": 1
              },
              "SpellMetaMagic": {
                "type": "byte",
                "value": 0
              }
            },
            {
              "__struct_id": 3,
              "Spell": {
                "type": "word",
                "value": 62
              },
              "SpellFlags": {
                "type": "byte",
                "value": 1
              },
              "SpellMetaMagic": {
                "type": "byte",
                "value": 0
              }
            },
            {
              "__struct_id": 3,
              "Spell": {
                "type": "word",
                "value": 130
              },
              "SpellFlags": {
                "type": "byte",
                "value": 1
              },
              "SpellMetaMagic": {
                "type": "byte",
                "value": 0
              }
            },
            {
              "__struct_id": 3,
              "Spell": {
                "type": "word",
                "value": 177
              },
              "SpellFlags": {
                "type": "byte",
                "value": 1
              },
              "SpellMetaMagic": {
                "type": "byte",
                "value": 0
              }
            }
          ]
        }
      }
    ]
  },
  "Comment": {
    "type": "cexostring",
    "value": ""
  },
  "Con": {
    "type": "byte",
    "value": 14
  },
  "Conversation": {
    "type": "resref",
    "value": "sf_gauntlet_conv"
  },
  "CRAdjust": {
    "type": "int",
    "value": 0
  },
  "CurrentHitPoints": {
    "type": "short",
    "value": 303
  },
  "DecayTime": {
    "type": "dword",
    "value": 5000
  },
  "Deity": {
    "type": "cexostring",
    "value": ""
  },
  "Description": {
    "type": "cexolocstring",
    "value": {}
  },
  "Dex": {
    "type": "byte",
    "value": 22
  },
  "Disarmable": {
    "type": "byte",
    "value": 0
  },
  "Equip_ItemList": {
    "type": "list",
    "value": [
      {
        "__struct_id": 2,
        "EquippedRes": {
          "type": "resref",
          "value": "nw_cloth016"
        }
      }
    ]
  },
  "FactionID": {
    "type": "word",
    "value": 3
  },
  "FeatList": {
    "type": "list",
    "value": [
      {
        "__struct_id": 1,
        "Feat": {
          "type": "word",
          "value": 199
        }
      },
      {
        "__struct_id": 1,
        "Feat": {
          "type": "word",
          "value": 3
        }
      },
      {
        "__struct_id": 1,
        "Feat": {
          "type": "word",
          "value": 4
        }
      },
      {
        "__struct_id": 1,
        "Feat": {
          "type": "word",
          "value": 6
        }
      },
      {
        "__struct_id": 1,
        "Feat": {
          "type": "word",
          "value": 8
        }
      },
      {
        "__struct_id": 1,
        "Feat": {
          "type": "word",
          "value": 214
        }
      },
      {
        "__struct_id": 1,
        "Feat": {
          "type": "word",
          "value": 215
        }
      },
      {
        "__struct_id": 1,
        "Feat": {
          "type": "word",
          "value": 374
        }
      },
      {
        "__struct_id": 1,
        "Feat": {
          "type": "word",
          "value": 297
        }
      },
      {
        "__struct_id": 1,
        "Feat": {
          "type": "word",
          "value": 971
        }
      },
      {
        "__struct_id": 1,
        "Feat": {
          "type": "word",
          "value": 584
        }
      },
      {
        "__struct_id": 1,
        "Feat": {
          "type": "word",
          "value": 973
        }
      },
      {
        "__struct_id": 1,
        "Feat": {
          "type": "word",
          "value": 587
        }
      },
      {
        "__struct_id": 1,
        "Feat": {
          "type": "word",
          "value": 755
        }
      },
      {
        "__struct_id": 1,
        "Feat": {
          "type": "word",
          "value": 756
        }
      },
      {
        "__struct_id": 1,
        "Feat": {
          "type": "word",
          "value": 757
        }
      },
      {
        "__struct_id": 1,
        "Feat": {
          "type": "word",
          "value": 758
        }
      },
      {
        "__struct_id": 1,
        "Feat": {
          "type": "word",
          "value": 759
        }
      },
      {
        "__struct_id": 1,
        "Feat": {
          "type": "word",
          "value": 761
        }
      },
      {
        "__struct_id": 1,
        "Feat": {
          "type": "word",
          "value": 206
        }
      },
      {
        "__struct_id": 1,
        "Feat": {
          "type": "word",
          "value": 204
        }
      },
      {
        "__struct_id": 1,
        "Feat": {
          "type": "word",
          "value": 212
        }
      },
      {
        "__struct_id": 1,
        "Feat": {
          "type": "word",
          "value": 697
        }
      },
      {
        "__struct_id": 1,
        "Feat": {
          "type": "word",
          "value": 698
        }
      },
      {
        "__struct_id": 1,
        "Feat": {
          "type": "word",
          "value": 17
        }
      },
      {
        "__struct_id": 1,
        "Feat": {
          "type": "word",
          "value": 20
        }
      },
      {
        "__struct_id": 1,
        "Feat": {
          "type": "word",
          "value": 21
        }
      },
      {
        "__struct_id": 1,
        "Feat": {
          "type": "word",
          "value": 344
        }
      },
      {
        "__struct_id": 1,
        "Feat": {
          "type": "word",
          "value": 23
        }
      },
      {
        "__struct_id": 1,
        "Feat": {
          "type": "word",
          "value": 260
        }
      },
      {
        "__struct_id": 1,
        "Feat": {
          "type": "word",
          "value": 207
        }
      },
      {
        "__struct_id": 1,
        "Feat": {
          "type": "word",
          "value": 216
        }
      },
      {
        "__struct_id": 1,
        "Feat": {
          "type": "word",
          "value": 209
        }
      },
      {
        "__struct_id": 1,
        "Feat": {
          "type": "word",
          "value": 258
        }
      },
      {
        "__struct_id": 1,
        "Feat": {
          "type": "word",
          "value": 296
        }
      },
      {
        "__struct_id": 1,
        "Feat": {
          "type": "word",
          "value": 32
        }
      },
      {
        "__struct_id": 1,
        "Feat": {
          "type": "word",
          "value": 208
        }
      },
      {
        "__struct_id": 1,
        "Feat": {
          "type": "word",
          "value": 39
        }
      },
      {
        "__struct_id": 1,
        "Feat": {
          "type": "word",
          "value": 201
        }
      },
      {
        "__struct_id": 1,
        "Feat": {
          "type": "word",
          "value": 41
        }
      },
      {
        "__struct_id": 1,
        "Feat": {
          "type": "word",
          "value": 45
        }
      },
      {
        "__struct_id": 1,
        "Feat": {
          "type": "word",
          "value": 49
        }
      },
      {
        "__struct_id": 1,
        "Feat": {
          "type": "word",
          "value": 46
        }
      },
      {
        "__struct_id": 1,
        "Feat": {
          "type": "word",
          "value": 211
        }
      }
    ]
  },
  "FirstName": {
    "type": "cexolocstring",
    "value": {
      "0": "Ravana Spectre"
    }
  },
  "fortbonus": {
    "type": "short",
    "value": 0
  },
  "Gender": {
    "type": "byte",
    "value": 0
  },
  "GoodEvil": {
    "type": "byte",
    "value": 100
  },
  "HitPoints": {
    "type": "short",
    "value": 303
  },
  "Int": {
    "type": "byte",
    "value": 10
  },
  "Interruptable": {
    "type": "byte",
    "value": 0
  },
  "IsImmortal": {
    "type": "byte",
    "value": 0
  },
  "IsPC": {
    "type": "byte",
    "value": 0
  },
  "LastName": {
    "type": "cexolocstring",
    "value": {}
  },
  "LawfulChaotic": {
    "type": "byte",
    "value": 50
  },
  "Lootable": {
    "type": "byte",
    "value": 0
  },
  "MaxHitPoints": {
    "type": "short",
    "value": 423
  },
  "NaturalAC": {
    "type": "byte",
    "value": 0
  },
  "NoPermDeath": {
    "type": "byte",
    "value": 0
  },
  "PaletteID": {
    "type": "byte",
    "value": 0
  },
  "PerceptionRange": {
    "type": "byte",
    "value": 11
  },
  "Phenotype": {
    "type": "int",
    "value": 0
  },
  "Plot": {
    "type": "byte",
    "value": 1
  },
  "PortraitId": {
    "type": "word",
    "value": 125
  },
  "Race": {
    "type": "byte",
    "value": 6
  },
  "refbonus": {
    "type": "short",
    "value": 0
  },
  "ScriptAttacked": {
    "type": "resref",
    "value": ""
  },
  "ScriptDamaged": {
    "type": "resref",
    "value": ""
  },
  "ScriptDeath": {
    "type": "resref",
    "value": ""
  },
  "ScriptDialogue": {
    "type": "resref",
    "value": "nw_c2_default4"
  },
  "ScriptDisturbed": {
    "type": "resref",
    "value": ""
  },
  "ScriptEndRound": {
    "type": "resref",
    "value": ""
  },
  "ScriptHeartbeat": {
    "type": "resref",
    "value": ""
  },
  "ScriptOnBlocked": {
    "type": "resref",
    "value": ""
  },
  "ScriptOnNotice": {
    "type": "resref",
    "value": ""
  },
  "ScriptRested": {
    "type": "resref",
    "value": ""
  },
  "ScriptSpawn": {
    "type": "resref",
    "value": ""
  },
  "ScriptSpellAt": {
    "type": "resref",
    "value": ""
  },
  "ScriptUserDefine": {
    "type": "resref",
    "value": ""
  },
  "SkillList": {
    "type": "list",
    "value": [
      {
        "__struct_id": 0,
        "Rank": {
          "type": "byte",
          "value": 30
        }
      },
      {
        "__struct_id": 0,
        "Rank": {
          "type": "byte",
          "value": 32
        }
      },
      {
        "__struct_id": 0,
        "Rank": {
          "type": "byte",
          "value": 0
        }
      },
      {
        "__struct_id": 0,
        "Rank": {
          "type": "byte",
          "value": 2
        }
      },
      {
        "__struct_id": 0,
        "Rank": {
          "type": "byte",
          "value": 32
        }
      },
      {
        "__struct_id": 0,
        "Rank": {
          "type": "byte",
          "value": 61
        }
      },
      {
        "__struct_id": 0,
        "Rank": {
          "type": "byte",
          "value": 61
        }
      },
      {
        "__struct_id": 0,
        "Rank": {
          "type": "byte",
          "value": 1
        }
      },
      {
        "__struct_id": 0,
        "Rank": {
          "type": "byte",
          "value": 31
        }
      },
      {
        "__struct_id": 0,
        "Rank": {
          "type": "byte",
          "value": 0
        }
      },
      {
        "__struct_id": 0,
        "Rank": {
          "type": "byte",
          "value": 31
        }
      },
      {
        "__struct_id": 0,
        "Rank": {
          "type": "byte",
          "value": 0
        }
      },
      {
        "__struct_id": 0,
        "Rank": {
          "type": "byte",
          "value": 31
        }
      },
      {
        "__struct_id": 0,
        "Rank": {
          "type": "byte",
          "value": 0
        }
      },
      {
        "__struct_id": 0,
        "Rank": {
          "type": "byte",
          "value": 0
        }
      },
      {
        "__struct_id": 0,
        "Rank": {
          "type": "byte",
          "value": 0
        }
      },
      {
        "__struct_id": 0,
        "Rank": {
          "type": "byte",
          "value": 0
        }
      },
      {
        "__struct_id": 0,
        "Rank": {
          "type": "byte",
          "value": 0
        }
      },
      {
        "__struct_id": 0,
        "Rank": {
          "type": "byte",
          "value": 0
        }
      },
      {
        "__struct_id": 0,
        "Rank": {
          "type": "byte",
          "value": 0
        }
      },
      {
        "__struct_id": 0,
        "Rank": {
          "type": "byte",
          "value": 0
        }
      },
      {
        "__struct_id": 0,
        "Rank": {
          "type": "byte",
          "value": 2
        }
      },
      {
        "__struct_id": 0,
        "Rank": {
          "type": "byte",
          "value": 1
        }
      },
      {
        "__struct_id": 0,
        "Rank": {
          "type": "byte",
          "value": 0
        }
      },
      {
        "__struct_id": 0,
        "Rank": {
          "type": "byte",
          "value": 0
        }
      },
      {
        "__struct_id": 0,
        "Rank": {
          "type": "byte",
          "value": 0
        }
      },
      {
        "__struct_id": 0,
        "Rank": {
          "type": "byte",
          "value": 0
        }
      },
      {
        "__struct_id": 0,
        "Rank": {
          "type": "byte",
          "value": 0
        }
      }
    ]
  },
  "SoundSetFile": {
    "type": "word",
    "value": 0
  },
  "SpecAbilityList": {
    "type": "list",
    "value": []
  },
  "StartingPackage": {
    "type": "byte",
    "value": 5
  },
  "Str": {
    "type": "byte",
    "value": 14
  },
  "Subrace": {
    "type": "cexostring",
    "value": ""
  },
  "Tag": {
    "type": "cexostring",
    "value": "thegauntletma001"
  },
  "Tail_New": {
    "type": "dword",
    "value": 0
  },
  "TemplateList": {
    "type": "list",
    "value": []
  },
  "TemplateResRef": {
    "type": "resref",
    "value": "thegauntletma001"
  },
  "WalkRate": {
    "type": "int",
    "value": 1
  },
  "willbonus": {
    "type": "short",
    "value": 0
  },
  "Wings_New": {
    "type": "dword",
    "value": 0
  },
  "Wis": {
    "type": "byte",
    "value": 22
  }
}
